pywxwork/__init__.py
pywxwork/base.py
pywxwork/token.py
pywxwork/application/menu.py
pywxwork/calendar/__init__.py
pywxwork/callback/WXBizMsgCrypt.py
pywxwork/callback/__init__.py
pywxwork/callback/ierror.py
pywxwork/contact/__init__.py
pywxwork/contact/async.py
pywxwork/contact/department.py
pywxwork/contact/linkedcorp.py
pywxwork/contact/tag.py
pywxwork/contact/user.py
pywxwork/customer/__init__.py
pywxwork/customer/customer.py
pywxwork/customer/tag.py
pywxwork/externalcontact/__init__.py
pywxwork/externalcontact/customer_acquisition/__init__.py
pywxwork/externalcontact/customer_acquisition_quota/__init__.py
pywxwork/externalcontact/group_welcome_template/__init__.py
pywxwork/externalcontact/groupchat/__init__.py
pywxwork/invoice/__init__.py
pywxwork/media/__init__.py
pywxwork/message/__init__.py
pywxwork/message/appchat.py
pywxwork/tool/living.py
pywxwork/webhook/__init__.py
pywxwork-1.0.18.dist-info/licenses/LICENSE
pywxwork-1.0.18.dist-info/METADATA
pywxwork-1.0.18.dist-info/WHEEL
pywxwork-1.0.18.dist-info/top_level.txt
pywxwork-1.0.18.dist-info/RECORD
