Metadata-Version: 2.4
Name: pywxwork
Version: 1.0.18
Summary: WeCom/Work WeChat API helpers (external contact, groupchat, etc.)
Author-email: Renqiukai <renqiukai@qq.com>
License: MIT
Keywords: wxwork,workwechat
Requires-Python: >=3.8
License-File: LICENSE
Requires-Dist: requests
Requires-Dist: loguru
Dynamic: license-file
